{"cameraMode":{"drawMode":0,"name":"Shaded","section":"Shading Mode"},"sceneLighting":false,"audioPlay":false,"sceneViewState":{"m_AlwaysRefresh":false,"showFog":true,"showSkybox":true,"showFlares":true,"showImageEffects":true,"showParticleSystems":true,"showVisualEffectGraphs":true,"m_FxEnabled":true},"in2DMode":false,"pivot":{"x":4.239999771118164,"y":6.0,"z":-12.0},"rotation":{"x":0.121135413646698,"y":-0.03275033459067345,"z":0.00399891659617424,"w":0.9920884966850281},"size":12.12435531616211,"orthographic":false}